DistributedSystemsEngineeringLectureNotesMit6824/README.md
DistributedSystemsEngineeringLectureNotesMit6824/__init__.py
DistributedSystemsEngineeringLectureNotesMit6824/__main__.py
DistributedSystemsEngineeringLectureNotesMit6824/file.epub
DistributedSystemsEngineeringLectureNotesMit6824/index.html
DistributedSystemsEngineeringLectureNotesMit6824/css/__init__.py
DistributedSystemsEngineeringLectureNotesMit6824/css/annotations.css
DistributedSystemsEngineeringLectureNotesMit6824/css/main.css
DistributedSystemsEngineeringLectureNotesMit6824/css/normalize.css
DistributedSystemsEngineeringLectureNotesMit6824/css/popup.css
DistributedSystemsEngineeringLectureNotesMit6824/font/__init__.py
DistributedSystemsEngineeringLectureNotesMit6824/font/fontello.eot
DistributedSystemsEngineeringLectureNotesMit6824/font/fontello.svg
DistributedSystemsEngineeringLectureNotesMit6824/font/fontello.ttf
DistributedSystemsEngineeringLectureNotesMit6824/font/fontello.woff
DistributedSystemsEngineeringLectureNotesMit6824/img/__init__.py
DistributedSystemsEngineeringLectureNotesMit6824/img/annotator-glyph-sprite.png
DistributedSystemsEngineeringLectureNotesMit6824/img/annotator-icon-sprite.png
DistributedSystemsEngineeringLectureNotesMit6824/img/apple-touch-icon.png
DistributedSystemsEngineeringLectureNotesMit6824/img/cancelfullscreen.png
DistributedSystemsEngineeringLectureNotesMit6824/img/close.png
DistributedSystemsEngineeringLectureNotesMit6824/img/fullscreen.png
DistributedSystemsEngineeringLectureNotesMit6824/img/loader.gif
DistributedSystemsEngineeringLectureNotesMit6824/img/menu-icon.png
DistributedSystemsEngineeringLectureNotesMit6824/img/save.png
DistributedSystemsEngineeringLectureNotesMit6824/img/saved.png
DistributedSystemsEngineeringLectureNotesMit6824/img/settings-s.png
DistributedSystemsEngineeringLectureNotesMit6824/img/settings.png
DistributedSystemsEngineeringLectureNotesMit6824/img/star.png
DistributedSystemsEngineeringLectureNotesMit6824/js/__init__.py
distributed_systems_engineering_lecture_notes_mit_6_824-2024.3.2.0.dist-info/METADATA
distributed_systems_engineering_lecture_notes_mit_6_824-2024.3.2.0.dist-info/WHEEL
distributed_systems_engineering_lecture_notes_mit_6_824-2024.3.2.0.dist-info/entry_points.txt
distributed_systems_engineering_lecture_notes_mit_6_824-2024.3.2.0.dist-info/top_level.txt
distributed_systems_engineering_lecture_notes_mit_6_824-2024.3.2.0.dist-info/RECORD
